zp_velodata/__init__.py
zp_velodata/api_models.py
zp_velodata/logging_config.py
zp_velodata/zp_client.py
zp_velodata-0.1.0.dist-info/METADATA
zp_velodata-0.1.0.dist-info/WHEEL
zp_velodata-0.1.0.dist-info/entry_points.txt
zp_velodata-0.1.0.dist-info/RECORD
